dateconverter/__init__.py
dateconverter/dateconverter.py
dateconverter-0.6.dist-info/LICENSE
dateconverter-0.6.dist-info/METADATA
dateconverter-0.6.dist-info/WHEEL
dateconverter-0.6.dist-info/top_level.txt
dateconverter-0.6.dist-info/RECORD
