Metadata-Version: 2.1
Name: dateconverter
Version: 0.6
Home-page: https://github.com/ig-rudenko/date_converter
Author: Igor Rudenko
Author-email: ig.rudenko1@yandex.ru
License: Apache 2.0
License-File: LICENSE
